tiny_ta/__init__.py
tiny_ta/calc.py
tiny_ta/candles.py
tiny_ta-0.0.2.dist-info/METADATA
tiny_ta-0.0.2.dist-info/WHEEL
tiny_ta-0.0.2.dist-info/top_level.txt
tiny_ta-0.0.2.dist-info/RECORD
